tree_sitter_agda-1.3.3.dist-info/top_level.txt
tree_sitter_agda-1.3.3.dist-info/RECORD
tree_sitter_agda-1.3.3.dist-info/LICENSE
tree_sitter_agda-1.3.3.dist-info/METADATA
tree_sitter_agda-1.3.3.dist-info/WHEEL
tree_sitter_agda/__init__.py
tree_sitter_agda/_binding.abi3.so
tree_sitter_agda/binding.c
tree_sitter_agda/__init__.pyi
tree_sitter_agda/py.typed
tree_sitter_agda/queries/highlights.scm
