Metadata-Version: 2.1
Name: tree-sitter-agda
Version: 1.3.3
Summary: Agda grammar for tree-sitter
Author: Lua Ting-Gian
License: MIT
Project-URL: Homepage, https://github.com/tree-sitter/tree-sitter-agda
Keywords: incremental,parsing,tree-sitter,agda
Classifier: Intended Audience :: Developers
Classifier: License :: OSI Approved :: MIT License
Classifier: Topic :: Software Development :: Compilers
Classifier: Topic :: Text Processing :: Linguistic
Classifier: Typing :: Typed
Requires-Python: >=3.9
License-File: LICENSE
Provides-Extra: core
Requires-Dist: tree-sitter~=0.22; extra == "core"
